pyaehw4a1/__init__.py
pyaehw4a1/__main__.py
pyaehw4a1/aehw4a1.py
pyaehw4a1/commands.py
pyaehw4a1/exceptions.py
pyaehw4a1/responses.py
pyaehw4a1-0.3.9.dist-info/LICENSE
pyaehw4a1-0.3.9.dist-info/METADATA
pyaehw4a1-0.3.9.dist-info/WHEEL
pyaehw4a1-0.3.9.dist-info/top_level.txt
pyaehw4a1-0.3.9.dist-info/RECORD
