Metadata-Version: 2.1
Name: pyaehw4a1
Version: 0.3.9
Summary: Python interface for Hisense AEH-W4A1 module
Home-page: https://github.com/bannhead/pyaehw4a1
Author: Davide Varricchio
Author-email: davide.varricchio@gmail.com
License: Apache 2.0
Platform: UNKNOWN
Classifier: Programming Language :: Python :: 3
Classifier: License :: OSI Approved :: Apache Software License
Classifier: Operating System :: OS Independent
Classifier: Topic :: Home Automation
